car_sound_dataset/__init__.py
car_sound_dataset/car_dataset.py
car_sound_dataset-1.5.0.dist-info/LICENSE
car_sound_dataset-1.5.0.dist-info/METADATA
car_sound_dataset-1.5.0.dist-info/WHEEL
car_sound_dataset-1.5.0.dist-info/top_level.txt
car_sound_dataset-1.5.0.dist-info/RECORD
