Metadata-Version: 2.1
Name: car-sound-dataset
Version: 1.5.0
Summary: You can use the car sound dataset with this Python package.
Home-page: https://github.com/blahutszabi/car_sound_dataset
Author: Szabolcs Blahut, Matyas Szakalos, Gyorgy Kalmar
Author-email: blahutszabi@gmail.com
Project-URL: Bug Tracker, https://github.com/blahutszabi/car_sound_dataset/issues
Classifier: Programming Language :: Python :: 3
Classifier: License :: OSI Approved :: MIT License
Classifier: Operating System :: OS Independent
Requires-Python: >=3.6
License-File: LICENSE
Requires-Dist: setuptools (>=42)
Requires-Dist: wheel
Requires-Dist: requests
Requires-Dist: gdown
Requires-Dist: matplotlib
Requires-Dist: scipy
Requires-Dist: numpy
Requires-Dist: sounddevice
Requires-Dist: soundfile
